[
  {
    "id": 1,
    "make": "Ford",
    "model": "F150",
    "year": 2021,
    "price": 35000,
    "vin": "1FTEW1C56KFA12345",
    "color": "Blue",
    "image": "images/vehicles/1/1.webp"
  },
  {
    "id": 2,
    "make": "Ford",
    "model": "F250",
    "year": 2022,
    "price": 45000,
    "vin": "1FT7W2B60NED67890",
    "color": "Red",
    "image": "images/vehicles/2/1.webp"
  },
  {
    "id": 3,
    "make": "Chevrolet",
    "model": "Silverado",
    "year": 2020,
    "price": 40000,
    "vin": "3GCUKSEC1LGZ23456",
    "color": "Black",
    "image": "images/vehicles/3/1.webp"
  },
  {
    "id": 4,
    "make": "Toyota",
    "model": "Tundra",
    "year": 2021,
    "price": 38000,
    "vin": "5TFDY5F15MX123456",
    "color": "White",
    "image": "images/vehicles/4/1.webp"
  },
  {
    "id": 5,
    "make": "Ram",
    "model": "1500",
    "year": 2019,
    "price": 37000,
    "vin": "1C6RR7PT6KS123456",
    "color": "Silver",
    "image": "images/vehicles/5/1.webp"
  },
  {
    "id": 6,
    "make": "GMC",
    "model": "Sierra",
    "year": 2022,
    "price": 46000,
    "vin": "3GTU9CED1NG123456",
    "color": "Green",
    "image": "images/vehicles/6/1.webp"
  },
  {
    "id": 7,
    "make": "Jeep",
    "model": "Grand Cherokee",
    "year": 2020,
    "price": 34000,
    "vin": "1C4RJFBGXLC123456",
    "color": "Gray",
    "image": "images/vehicles/7/1.webp"
  },
  {
    "id": 8,
    "make": "Ford",
    "model": "Bronco",
    "year": 2022,
    "price": 42000,
    "vin": "1FMCU9E67NLB12345",
    "color": "Orange",
    "image": "images/vehicles/8/1.webp"
  },
  {
    "id": 9,
    "make": "Chevrolet",
    "model": "Tahoe",
    "year": 2021,
    "price": 48000,
    "vin": "1GNSKCKD7MR123456",
    "color": "Navy Blue",
    "image": "images/vehicles/9/1.webp"
  },
  {
    "id": 10,
    "make": "Toyota",
    "model": "4Runner",
    "year": 2019,
    "price": 36000,
    "vin": "JTEBU5JRXK5612345",
    "color": "Dark Green",
    "image": "images/vehicles/10/1.webp"
  },
  {
    "id": 11,
    "make": "Nissan",
    "model": "Titan",
    "year": 2020,
    "price": 39000,
    "vin": "1N6AA1ED9LN123456",
    "color": "Beige",
    "image": "images/vehicles/11/1.webp"
  },
  {
    "id": 12,
    "make": "Dodge",
    "model": "Durango",
    "year": 2019,
    "price": 32000,
    "vin": "1C4RDJFG3KC123456",
    "color": "Red",
    "image": "images/vehicles/12/1.webp"
  },
  {
    "id": 13,
    "make": "Ford",
    "model": "Explorer",
    "year": 2021,
    "price": 41000,
    "vin": "1FM5K8D8XMG123456",
    "color": "Black",
    "image": "images/vehicles/13/1.webp"
  },
  {
    "id": 14,
    "make": "Chevrolet",
    "model": "Suburban",
    "year": 2022,
    "price": 52000,
    "vin": "1GNSCJKD5NR123456",
    "color": "Silver",
    "image": "images/vehicles/14/1.webp"
  },
  {
    "id": 15,
    "make": "Jeep",
    "model": "Wrangler",
    "year": 2021,
    "price": 43000,
    "vin": "1C4HJXEG3MW123456",
    "color": "Blue",
    "image": "images/vehicles/15/1.webp"
  }
]
